llm_video_frames.py
llm_video_frames-0.1.dist-info/licenses/LICENSE
llm_video_frames-0.1.dist-info/METADATA
llm_video_frames-0.1.dist-info/WHEEL
llm_video_frames-0.1.dist-info/entry_points.txt
llm_video_frames-0.1.dist-info/top_level.txt
llm_video_frames-0.1.dist-info/RECORD
