Metadata-Version: 2.4
Name: llm-video-frames
Version: 0.1
Summary: LLM plugin to turn a video into individual frames
Author: Simon Willison
License-Expression: Apache-2.0
Project-URL: Homepage, https://github.com/simonw/llm-video-frames
Project-URL: Changelog, https://github.com/simonw/llm-video-frames/releases
Project-URL: Issues, https://github.com/simonw/llm-video-frames/issues
Project-URL: CI, https://github.com/simonw/llm-video-frames/actions
Requires-Python: >=3.9
License-File: LICENSE
Requires-Dist: llm>=0.25
Provides-Extra: test
Requires-Dist: pytest; extra == "test"
Dynamic: license-file
